{
  "scene_26_2_rgb": [
    {
      "bbox": {
        "cx": 626.8790283203125,
        "cy": 756.0059814453125,
        "w": 64.079345703125,
        "h": 147.49462890625,
        "angle": 0.0
      },
      "category": "an USB drive",
      "conf": 0.3963567912578583
    },
    {
      "bbox": {
        "cx": 1322.9567260742188,
        "cy": 632.5745086669922,
        "w": 126.7911376953125,
        "h": 343.5677795410156,
        "angle": 0.0
      },
      "category": "a black pen",
      "conf": 0.6059635281562805
    }
  ]
}