{
  "scene_44_2_rgb": [
    {
      "bbox": {
        "cx": 647.1970520019531,
        "cy": 343.655029296875,
        "w": 93.88690185546875,
        "h": 109.10919189453125,
        "angle": 0.0
      },
      "category": "a small green triangular prism",
      "conf": 0.252975732088089
    },
    {
      "bbox": {
        "cx": 1266.9660034179688,
        "cy": 208.00543975830078,
        "w": 135.6639404296875,
        "h": 145.8737030029297,
        "angle": 0.0
      },
      "category": "a large blue triangular prism",
      "conf": 0.1934463232755661
    },
    {
      "bbox": {
        "cx": 643.64501953125,
        "cy": 618.7491760253906,
        "w": 282.055908203125,
        "h": 156.57440185546875,
        "angle": 0.0
      },
      "category": "a long red block",
      "conf": 0.23369108140468597
    }
  ]
}