[
  {
    "bbox": {
      "cx": 1382.3927001953125,
      "cy": 298.3555679321289,
      "w": 170.701171875,
      "h": 102.61698913574219,
      "angle": 0.0
    },
    "category": "a long blue block",
    "conf": 0.1930982619524002
  },
  {
    "bbox": {
      "cx": 669.2608642578125,
      "cy": 597.1030578613281,
      "w": 112.3736572265625,
      "h": 92.03912353515625,
      "angle": 0.0
    },
    "category": "a small red triangular prism",
    "conf": 0.16501514613628387
  },
  {
    "bbox": {
      "cx": 1035.8139173330596,
      "cy": 833.9437741387342,
      "w": 496.6333386894805,
      "h": 390.54025942828105,
      "angle": -4.044522554499873
    },
    "category": "a yellow basket",
    "conf": 0.15556950867176056
  },
  {
    "bbox": {
      "cx": 497.4020919167459,
      "cy": 383.9924690728901,
      "w": 103.04864830094415,
      "h": 147.4832190551784,
      "angle": -27.799130351638663
    },
    "category": "a red cylinder",
    "conf": null
  },
  {
    "bbox": {
      "cx": 1344.4857406751416,
      "cy": 500.3544003375481,
      "w": 95.25242614008874,
      "h": 178.15740953480514,
      "angle": 2.629247280689453
    },
    "category": "a long blue block",
    "conf": null
  },
  {
    "bbox": {
      "cx": 793.2750860730612,
      "cy": 266.63753978057,
      "w": 85.98181801358804,
      "h": 107.60677143166401,
      "angle": 0.0
    },
    "category": "a small yellow triangular prism",
    "conf": null
  },
  {
    "bbox": {
      "cx": 1142.2707076336487,
      "cy": 205.327501559417,
      "w": 98.35206600864771,
      "h": 95.33709523981331,
      "angle": 0.0
    },
    "category": "a small red triangular prism",
    "conf": null
  },
  {
    "bbox": {
      "cx": 997.3078265250901,
      "cy": 532.229351823768,
      "w": 94.94425675228707,
      "h": 174.28513880556585,
      "angle": -32.96304206176546
    },
    "category": "a long green block",
    "conf": null
  }
]